{
    "links": [
        {
            "name": "Home",
            "link": "/"
        }
    ],
    "apps": [
        {
            "name": "Portainer",
            "url": "https://portainer.lab.home",
            "image": "apps/portainer.svg"
        },
        {
            "name": "File Browser",
            "url": "https://files.lab.home",
            "image": "apps/file-browser.png"
        },
        {
            "name": "Pi Hole",
            "url": "https://ph.lab.home/admin",
            "image": "apps/pi-hole.png",
            "type": "pi-hole",
            "apiKey": "aaa"
        }
    ]
}